dreamer4/__init__.py
dreamer4/dreamer4.py
dreamer4/mocks.py
dreamer4/trainers.py
dreamer4-0.1.30.dist-info/METADATA
dreamer4-0.1.30.dist-info/WHEEL
dreamer4-0.1.30.dist-info/licenses/LICENSE
dreamer4-0.1.30.dist-info/RECORD
