Metadata-Version: 2.4
Name: dreamer4
Version: 0.1.30
Summary: Dreamer 4
Project-URL: Homepage, https://pypi.org/project/dreamer4/
Project-URL: Repository, https://github.com/lucidrains/dreamer4
Author-email: Phil Wang <lucidrains@gmail.com>
License: MIT License
License-File: LICENSE
Keywords: artificial intelligence,attention mechanism,deep learning,model-based reinforcement learning,transformer,world models
Classifier: Development Status :: 4 - Beta
Classifier: Intended Audience :: Developers
Classifier: License :: OSI Approved :: MIT License
Classifier: Programming Language :: Python :: 3.9
Classifier: Topic :: Scientific/Engineering :: Artificial Intelligence
Requires-Python: >=3.9
Requires-Dist: accelerate
Requires-Dist: adam-atan2-pytorch>=0.2.2
Requires-Dist: assoc-scan
Requires-Dist: discrete-continuous-embed-readout>=0.1.12
Requires-Dist: einops>=0.8.1
Requires-Dist: einx>=0.3.0
Requires-Dist: ema-pytorch
Requires-Dist: hl-gauss-pytorch
Requires-Dist: hyper-connections>=0.3.12
Requires-Dist: torch>=2.4
Requires-Dist: torchvision
Requires-Dist: vit-pytorch>=1.15.3
Requires-Dist: x-mlps-pytorch>=0.0.29
Provides-Extra: examples
Provides-Extra: test
Requires-Dist: pytest; extra == 'test'
Requires-Dist: pytest-shard; extra == 'test'
